[
 {"id": 0, "imageUrl": "img/1cat.png", "name": "Katrine", "category": 1, "sex": "female"}, 
 {"id": 2, "imageUrl": "img/2dog.png", "name": "Jennifer", "category": 2, "sex": "female"},
 {"id": 3, "imageUrl": "img/3dog.png", "name": "Woody", "category": 2, "sex": "male"},
 {"id": 4, "imageUrl": "img/4dog.png", "name": "Sophia", "category": 2, "sex": "female"}, 
 {"id": 5, "imageUrl": "img/5cat.png", "name": "Timmy", "category": 1, "sex": "male"}, 
 {"id": 6, "imageUrl": "img/6dog.png", "name": "Charly", "category": 2, "sex": "male"}, 
 {"id": 7, "imageUrl": "img/7dog.png", "name": "Scarlett", "category": 2, "sex": "female"}, 
 {"id": 8, "imageUrl": "img/8cat.png", "name": "Freddie", "category": 1, "sex": "male"},
 {"id": 9, "imageUrl": "img/9cat.png", "name": "Lisa", "category": 1, "sex": "female"},
 {"id": 10, "imageUrl": "img/10cat.png", "name": "Tom", "category": 1, "sex": "male"},
 {"id": 11, "imageUrl": "img/11dog.png", "name": "Johnny", "category": 2, "sex": "male"},
 {"id": 12, "imageUrl": "img/12dog.png", "name": "Amber", "category": 2, "sex": "female"},
 {"id": 13, "imageUrl": "img/13cat.png", "name": "Martin", "category": 1, "sex": "male"},
 {"id": 14, "imageUrl": "img/14dog.png", "name": "Larry", "category": 2, "sex": "male"},
 {"id": 15, "imageUrl": "img/15cat.png", "name": "Molly", "category": 1, "sex": "female"},
 {"id": 16, "imageUrl": "img/16cat.png", "name": "Felicity", "category": 1, "sex": "female"},
 {"id": 17, "imageUrl": "img/17cat.png", "name": "Meggie", "category": 1, "sex": "female"},
 {"id": 18, "imageUrl": "img/18dog.png", "name": "Abby", "category": 2, "sex": "female"},
 {"id": 19, "imageUrl": "img/19cat.png", "name": "Cinnamon", "category": 1, "sex": "female"}
 ]